cyclone/__init__.py
cyclone/capture.py
cyclone/networking.py
cyclone/session.py
usecyclone-0.1.1.dist-info/METADATA
usecyclone-0.1.1.dist-info/WHEEL
usecyclone-0.1.1.dist-info/top_level.txt
usecyclone-0.1.1.dist-info/RECORD
