Metadata-Version: 2.1
Name: usecyclone
Version: 0.1.1
Author: Cyclone Technologies, LLC
Author-email: tony@usecyclone.dev
Requires-Dist: watchdog
Requires-Dist: posthog
Requires-Dist: py-machineid
